{
  "cells": [
    {
      "h3": "894ba0a45b3ffff",
      "res": 9,
      "count": 1,
      "center": {
        "lat": 25.06959469545563,
        "lng": 121.52839048089892
      },
      "categories": {
        "culture": 1
      },
      "points": [
        {
          "id": 7400024,
          "title": "圓山分隊",
          "category": "culture",
          "location": "臺北市",
          "coords": [
            25.068530708073396,
            121.52917745468906
          ],
          "address": "臺北市中山區民族東路41號",
          "layoutType": "",
          "hours": "詳見官方網站",
          "description": "本位置資訊僅供參考，實際情形以現場公告及標示為準",
          "image": "",
          "management": "",
          "phone": "",
          "notes": "本位置資訊僅供參考，實際情形以現場公告及標示為準"
        }
      ]
    },
    {
      "h3": "894ba0a4543ffff",
      "res": 9,
      "count": 1,
      "center": {
        "lat": 25.054547067928073,
        "lng": 121.51972884036093
      },
      "categories": {
        "culture": 1
      },
      "points": [
        {
          "id": 7400031,
          "title": "建成分隊",
          "category": "culture",
          "location": "臺北市",
          "coords": [
            25.05476444551777,
            121.51824595997324
          ],
          "address": "臺北市大同區承德路二段35號",
          "layoutType": "",
          "hours": "詳見官方網站",
          "description": "本位置資訊僅供參考，實際情形以現場公告及標示為準",
          "image": "",
          "management": "",
          "phone": "",
          "notes": "本位置資訊僅供參考，實際情形以現場公告及標示為準"
        }
      ]
    },
    {
      "h3": "894ba0a45dbffff",
      "res": 9,
      "count": 1,
      "center": {
        "lat": 25.060566099519775,
        "lng": 121.51331544040765
      },
      "categories": {
        "culture": 1
      },
      "points": [
        {
          "id": 7400033,
          "title": "大同分隊",
          "category": "culture",
          "location": "臺北市",
          "coords": [
            25.06148762242709,
            121.51373474718626
          ],
          "address": "臺北市大同區重慶北路二段223號",
          "layoutType": "",
          "hours": "詳見官方網站",
          "description": "本位置資訊僅供參考，實際情形以現場公告及標示為準",
          "image": "",
          "management": "",
          "phone": "",
          "notes": "本位置資訊僅供參考，實際情形以現場公告及標示為準"
        }
      ]
    }
  ],
  "updatedAt": "2026-07-01T18:21:02.271Z"
}