{
  "cells": [
    {
      "h3": "874ba0a40ffffff",
      "res": 7,
      "count": 2,
      "center": {
        "lat": 25.041169357299943,
        "lng": 121.51751796001166
      },
      "categories": {
        "other": 2
      }
    },
    {
      "h3": "874ba0a46ffffff",
      "res": 7,
      "count": 1,
      "center": {
        "lat": 25.035316260299084,
        "lng": 121.49494641710433
      },
      "categories": {
        "other": 1
      }
    },
    {
      "h3": "874ba0a63ffffff",
      "res": 7,
      "count": 1,
      "center": {
        "lat": 25.07510985385678,
        "lng": 121.51016348483485
      },
      "categories": {
        "other": 1
      }
    },
    {
      "h3": "874ba0a58ffffff",
      "res": 7,
      "count": 1,
      "center": {
        "lat": 24.99314935016505,
        "lng": 121.53983725106309
      },
      "categories": {
        "other": 1
      }
    },
    {
      "h3": "874ba0a61ffffff",
      "res": 7,
      "count": 1,
      "center": {
        "lat": 25.095000640763953,
        "lng": 121.51777365010938
      },
      "categories": {
        "other": 1
      }
    }
  ],
  "updatedAt": "2026-07-01T18:21:04.726Z"
}