{
  "cells": [
    {
      "h3": "874ba56b3ffffff",
      "res": 7,
      "count": 1,
      "center": {
        "lat": 25.168669453822048,
        "lng": 121.52564136162466
      },
      "categories": {
        "other": 1
      }
    },
    {
      "h3": "874ba569cffffff",
      "res": 7,
      "count": 2,
      "center": {
        "lat": 25.146471698390936,
        "lng": 121.5781712392484
      },
      "categories": {
        "other": 2
      }
    },
    {
      "h3": "874ba1d30ffffff",
      "res": 7,
      "count": 9,
      "center": {
        "lat": 25.08445403167183,
        "lng": 121.61547983814485
      },
      "categories": {
        "other": 9
      }
    }
  ],
  "updatedAt": "2026-07-01T18:20:50.922Z"
}