{
  "cells": [
    {
      "h3": "894ba0b483bffff",
      "res": 9,
      "count": 1,
      "center": {
        "lat": 25.135912840062122,
        "lng": 121.47824472196827
      },
      "categories": {
        "other": 1
      },
      "points": [
        {
          "id": 1600410,
          "title": "忠義公園",
          "category": "other",
          "location": "北投",
          "coords": [
            25.135104,
            121.477761
          ],
          "address": "臺北市北投區中央北路四段32號旁",
          "layoutType": "",
          "hours": "0:00~24:00",
          "description": "本位置資訊僅供參考，實際情形以現場公告及標示為準",
          "image": "",
          "management": "工務局公園處陽明山管理所",
          "phone": "28832130",
          "notes": "本位置資訊僅供參考，實際情形以現場公告及標示為準"
        }
      ]
    },
    {
      "h3": "894ba0b48dbffff",
      "res": 9,
      "count": 1,
      "center": {
        "lat": 25.136568273261243,
        "lng": 121.46107496215762
      },
      "categories": {
        "other": 1
      },
      "points": [
        {
          "id": 1600447,
          "title": "竹圍站",
          "category": "other",
          "location": "淡水",
          "coords": [
            25.137049,
            121.459651
          ],
          "address": "新北市淡水區民權路50號",
          "layoutType": "",
          "hours": "06:00~23:00",
          "description": "本位置資訊僅供參考，實際情形以現場公告及標示為準",
          "image": "",
          "management": "臺北大眾捷運股份有限公司(紅綠線)",
          "phone": "25363001#8653",
          "notes": "本位置資訊僅供參考，實際情形以現場公告及標示為準"
        }
      ]
    },
    {
      "h3": "894ba0b4873ffff",
      "res": 9,
      "count": 1,
      "center": {
        "lat": 25.13223591882154,
        "lng": 121.4739340369858
      },
      "categories": {
        "other": 1
      },
      "points": [
        {
          "id": 1600449,
          "title": "忠義站",
          "category": "other",
          "location": "北投",
          "coords": [
            25.131062,
            121.473214
          ],
          "address": "臺北市北投區中央北路4段301號",
          "layoutType": "",
          "hours": "06:00~23:00",
          "description": "本位置資訊僅供參考，實際情形以現場公告及標示為準",
          "image": "",
          "management": "臺北大眾捷運股份有限公司(紅綠線)",
          "phone": "25363001#8653",
          "notes": "本位置資訊僅供參考，實際情形以現場公告及標示為準"
        }
      ]
    },
    {
      "h3": "894ba0b4827ffff",
      "res": 9,
      "count": 1,
      "center": {
        "lat": 25.137587040674042,
        "lng": 121.48469315145176
      },
      "categories": {
        "other": 1
      },
      "points": [
        {
          "id": 1600450,
          "title": "復興崗站",
          "category": "other",
          "location": "北投",
          "coords": [
            25.13766,
            121.485365
          ],
          "address": "臺北市北投區中央北路3段53巷10號",
          "layoutType": "",
          "hours": "06:00~23:00",
          "description": "本位置資訊僅供參考，實際情形以現場公告及標示為準",
          "image": "",
          "management": "臺北大眾捷運股份有限公司(紅綠線)",
          "phone": "25363001#8653",
          "notes": "本位置資訊僅供參考，實際情形以現場公告及標示為準"
        }
      ]
    }
  ],
  "updatedAt": "2026-07-01T18:20:45.545Z"
}